scrive/__init__.py
scrive/core.py
scrive/factory.py
scrive/macros.py
scrive/patterns.py
scrive-0.2.0.dist-info/METADATA
scrive-0.2.0.dist-info/WHEEL
scrive-0.2.0.dist-info/top_level.txt
scrive-0.2.0.dist-info/RECORD
