Metadata-Version: 2.4
Name: scrive
Version: 0.2.0
Summary: A Pythonic regex pattern builder
Home-page: https://github.com/DomBom16/scrive
Author: Domenic Urso
Author-email: domenicjurso@gmail.com
Project-URL: Bug Reports, https://github.com/DomBom16/scrive/issues
Project-URL: Source, https://github.com/DomBom16/scrive
Project-URL: Documentation, https://github.com/DomBom16/scrive#readme
Keywords: regex regexp regular-expressions pattern-matching fluent-api method-chaining pythonic operator-overloading
Classifier: Development Status :: 4 - Beta
Classifier: Intended Audience :: Developers
Classifier: License :: OSI Approved :: MIT License
Classifier: Operating System :: OS Independent
Classifier: Programming Language :: Python :: 3
Classifier: Programming Language :: Python :: 3.7
Classifier: Programming Language :: Python :: 3.8
Classifier: Programming Language :: Python :: 3.9
Classifier: Programming Language :: Python :: 3.10
Classifier: Programming Language :: Python :: 3.11
Classifier: Programming Language :: Python :: 3.12
Classifier: Topic :: Software Development :: Libraries :: Python Modules
Classifier: Topic :: Text Processing
Classifier: Topic :: Utilities
Classifier: Typing :: Typed
Requires-Python: >=3.7
Provides-Extra: dev
Requires-Dist: pytest>=6.0; extra == "dev"
Requires-Dist: black>=21.0; extra == "dev"
Requires-Dist: flake8>=3.8; extra == "dev"
Requires-Dist: mypy>=0.910; extra == "dev"
Dynamic: author
Dynamic: author-email
Dynamic: classifier
Dynamic: description
Dynamic: description-content-type
Dynamic: home-page
Dynamic: keywords
Dynamic: project-url
Dynamic: provides-extra
Dynamic: requires-python
Dynamic: summary
